ragformance/__init__.py
ragformance/cli/__init__.py
ragformance/cli/run.py
ragformance/dataloaders/__init__.py
ragformance/dataloaders/beir_dataloader.py
ragformance/dataloaders/downloads.py
ragformance/dataloaders/huggingface_dataloader.py
ragformance/eval/__init__.py
ragformance/eval/deepeval.py
ragformance/eval/trec_eval.py
ragformance/eval/visualization.py
ragformance/generators/__init__.py
ragformance/generators/base_config.py
ragformance/generators/data_generator_interface.py
ragformance/generators/aida/__init__.py
ragformance/generators/aida/capella_pdf_qa_generator.py
ragformance/generators/aida/config.py
ragformance/generators/aida/generator.py
ragformance/generators/alpha/__init__.py
ragformance/generators/alpha/config.py
ragformance/generators/alpha/generator.py
ragformance/generators/alpha/main.py
ragformance/generators/alpha/parsing_engine.py
ragformance/generators/alpha/prompts.py
ragformance/generators/based_llm_and_summary/__init__.py
ragformance/generators/based_llm_and_summary/buildSyntheticDataset.py
ragformance/generators/based_llm_and_summary/config.py
ragformance/generators/based_llm_and_summary/generator.py
ragformance/generators/error_code/__init__.py
ragformance/generators/error_code/config.py
ragformance/generators/error_code/generator.py
ragformance/generators/error_code/main.py
ragformance/generators/error_code/parsing_engine.py
ragformance/generators/error_code/question_generation.py
ragformance/generators/llm_prompt/__init__.py
ragformance/generators/llm_prompt/config.py
ragformance/generators/llm_prompt/corpus_builder.py
ragformance/generators/llm_prompt/generate_synthetic_answers.py
ragformance/generators/llm_prompt/generate_synthetic_queries.py
ragformance/generators/llm_prompt/generator.py
ragformance/generators/llm_prompt/file_processors/file_processor_interface.py
ragformance/generators/llm_prompt/file_processors/md_processor.py
ragformance/generators/llm_prompt/file_processors/pdf_processor.py
ragformance-0.1.105.dist-info/licenses/LICENSE
ragformance-0.1.105.dist-info/METADATA
ragformance-0.1.105.dist-info/WHEEL
ragformance-0.1.105.dist-info/entry_points.txt
ragformance-0.1.105.dist-info/top_level.txt
ragformance-0.1.105.dist-info/RECORD
