Metadata-Version: 2.4
Name: ragformance
Version: 0.1.105
Summary: A library for generating dataset and evaluating these datasets on RAG based solutions
Author-email: FOR Team <jonathan.sprauel@irt-saintexupery.com>
Project-URL: Homepage, https://github.com/FOR-sight-ai/RAGFORmance
Project-URL: Bug Tracker, https://github.com/FOR-sight-ai/RAGFORmance/issues
Classifier: Programming Language :: Python :: 3
Classifier: License :: OSI Approved :: MIT License
Classifier: Operating System :: OS Independent
Requires-Python: <3.13,>=3.9
License-File: LICENSE
Requires-Dist: tqdm
Requires-Dist: pydantic
Requires-Dist: litellm
Provides-Extra: rag-haystack
Requires-Dist: farm-haystack==1.22.1; extra == "rag-haystack"
Requires-Dist: sentence-transformers==2.2.2; extra == "rag-haystack"
Provides-Extra: rag-naive
Requires-Dist: sentence-transformers==2.2.2; extra == "rag-naive"
Provides-Extra: generators-ragas
Requires-Dist: ragas; extra == "generators-ragas"
Requires-Dist: langchain-community; extra == "generators-ragas"
Provides-Extra: generators-llm-summary
Requires-Dist: unstructured[md]; extra == "generators-llm-summary"
Provides-Extra: generators-aida
Requires-Dist: chromadb; extra == "generators-aida"
Provides-Extra: visualization
Requires-Dist: sentence-transformers==2.2.2; extra == "visualization"
Requires-Dist: plotly; extra == "visualization"
Provides-Extra: huggingface
Requires-Dist: huggingface_hub; extra == "huggingface"
Requires-Dist: datasets; extra == "huggingface"
Provides-Extra: deepeval
Requires-Dist: deepeval; extra == "deepeval"
Provides-Extra: trec-eval
Requires-Dist: pytrec_eval; extra == "trec-eval"
Provides-Extra: dev
Requires-Dist: forcolate; extra == "dev"
Requires-Dist: pre-commit>=2.1.1; extra == "dev"
Provides-Extra: phoenix
Requires-Dist: arize-phoenix; extra == "phoenix"
Requires-Dist: arize-phoenix-otel; extra == "phoenix"
Requires-Dist: openinference-instrumentation-litellm; extra == "phoenix"
Provides-Extra: all
Requires-Dist: farm-haystack==1.22.1; extra == "all"
Requires-Dist: sentence-transformers==2.2.2; extra == "all"
Requires-Dist: plotly; extra == "all"
Requires-Dist: ragas; extra == "all"
Requires-Dist: chromadb; extra == "all"
Requires-Dist: unstructured[md]; extra == "all"
Requires-Dist: huggingface_hub; extra == "all"
Requires-Dist: datasets; extra == "all"
Requires-Dist: forcolate; extra == "all"
Requires-Dist: arize-phoenix; extra == "all"
Requires-Dist: arize-phoenix-otel; extra == "all"
Requires-Dist: openinference-instrumentation-litellm; extra == "all"
Requires-Dist: deepeval; extra == "all"
Requires-Dist: pytrec_eval; extra == "all"
Requires-Dist: pre-commit>=2.1.1; extra == "all"
Dynamic: license-file
